swagger_client/__init__.py
swagger_client/api_client.py
swagger_client/configuration.py
swagger_client/rest.py
swagger_client/api/__init__.py
swagger_client/api/apontamentos_api.py
swagger_client/api/converso_de_fatores_de_emisso_api.py
swagger_client/api/metas_api.py
swagger_client/api/relatrio_api.py
swagger_client/models/__init__.py
wem_saas-0.1.dist-info/METADATA
wem_saas-0.1.dist-info/WHEEL
wem_saas-0.1.dist-info/top_level.txt
wem_saas-0.1.dist-info/RECORD
