Metadata-Version: 2.1
Name: wem-saas
Version: 0.1
Summary: WEM
Home-page: UNKNOWN
Author-email: brendonsilva@weg.net
License: UNKNOWN
Keywords: Swagger,WEM
Platform: UNKNOWN
Requires-Dist: urllib3 >=1.15
Requires-Dist: six >=1.10
Requires-Dist: certifi
Requires-Dist: python-dateutil
